dotli/__init__.py
dotli/__version__.py
dotli/ambiguous_obj.py
dotli/dotli.py
dotli/errors.py
dotli-1.1.dist-info/LICENSE
dotli-1.1.dist-info/METADATA
dotli-1.1.dist-info/WHEEL
dotli-1.1.dist-info/top_level.txt
dotli-1.1.dist-info/RECORD
