Metadata-Version: 2.1
Name: dotli
Version: 1.1
Summary: An easy way to flatten and unflatten dicts and lists
Home-page: https://github.com/spacemanspiff2007/dotli
Author: spaceman_spiff
License: UNKNOWN
Project-URL: GitHub, https://github.com/spacemanspiff2007/dotli
Keywords: json,flatten,unflatten,unpack
Platform: UNKNOWN
Classifier: Development Status :: 4 - Beta
Classifier: License :: OSI Approved :: GNU General Public License v3 or later (GPLv3+)
Classifier: Operating System :: OS Independent
Classifier: Programming Language :: Python :: 3.5
Classifier: Programming Language :: Python :: 3.6
Classifier: Programming Language :: Python :: 3.7
Classifier: Programming Language :: Python :: 3.8
Classifier: Programming Language :: Python :: 3.9
Classifier: Programming Language :: Python :: 3 :: Only
Classifier: Topic :: Software Development :: Libraries
